cfel_fmt/__init__.py
cfel_fmt/crystfel_stream.py
cfel_fmt/geometry.py
cfel_fmt-2.2.0.dist-info/licenses/LICENSE
cfel_fmt-2.2.0.dist-info/WHEEL
cfel_fmt-2.2.0.dist-info/METADATA
cfel_fmt-2.2.0.dist-info/RECORD
