Metadata-Version: 2.4
Name: cfel_fmt
Version: 2.2.0
Summary: Parsing file formats associated with CFEL software projects
Author-email: "Coherent Imaging Division, CFEL" <sc@cfel.de>
Maintainer-email: European XFEL GmbH <da-support@xfel.eu>
Requires-Python: >= 3.9
License-Expression: GPL-3.0-or-later
Classifier: Programming Language :: Python :: 3
Classifier: Intended Audience :: Science/Research
License-File: LICENSE
Requires-Dist: numpy
Requires-Dist: pandas
Requires-Dist: sphinx ; extra == "docs"
Requires-Dist: furo ; extra == "docs"
Requires-Dist: m2r2 ; extra == "docs"
Requires-Dist: setuptools ; extra == "docs"
Requires-Dist: docutils<0.21 ; extra == "docs"
Requires-Dist: black ; extra == "lint"
Requires-Dist: pylint ; extra == "lint"
Requires-Dist: pylint-gitlab ; extra == "lint"
Requires-Dist: mypy ; extra == "lint"
Requires-Dist: pytest ; extra == "test"
Requires-Dist: pytest-cov ; extra == "test"
Project-URL: Source, https://gitlab.desy.de/cfel-sc-public/cfelpyutils
Provides-Extra: docs
Provides-Extra: lint
Provides-Extra: test
